midoghanam/__init__.py
midoghanam-0.0.5.dist-info/licenses/LICENSE
midoghanam-0.0.5.dist-info/METADATA
midoghanam-0.0.5.dist-info/WHEEL
midoghanam-0.0.5.dist-info/top_level.txt
midoghanam-0.0.5.dist-info/RECORD
