Metadata-Version: 2.4
Name: midoghanam
Version: 0.0.5
Summary: مكتبتي الشخصية – midoghanam
Home-page: https://github.com/mido-ghanam
Author: Mohamed Ahmed Ghanam
Author-email: Mohamed Ahmed Ghanam <mghanam883@outlook.com>
License: MIT
Classifier: Programming Language :: Python :: 3
Classifier: License :: OSI Approved :: MIT License
Classifier: Operating System :: OS Independent
Requires-Python: >=3.6
License-File: LICENSE
Requires-Dist: setuptools>=59.6.0
Dynamic: author
Dynamic: home-page
Dynamic: license-file
Dynamic: requires-python
